dcad_parser/__init__.py
dcad_parser/fields.py
dcad_parser/generate_sqlalchemy.py
dcad_parser/parser/__init__.py
dcad_parser/parser/metadata_parser.py
dcad_parser/parser/table_parser.py
dcad_parser/parser/tests/__init__.py
dcad_parser/parser/tests/test_metadata_parser.py
dcad_parser/parser/tests/test_table_parser.py
dcad_parser/tests/__init__.py
dcad_parser/tests/test_fields.py
dcad_parser_hydrospanner-0.1.1.dist-info/LICENSE
dcad_parser_hydrospanner-0.1.1.dist-info/METADATA
dcad_parser_hydrospanner-0.1.1.dist-info/WHEEL
dcad_parser_hydrospanner-0.1.1.dist-info/entry_points.txt
dcad_parser_hydrospanner-0.1.1.dist-info/top_level.txt
dcad_parser_hydrospanner-0.1.1.dist-info/RECORD
